docker_ci_deploy/__init__.py
docker_ci_deploy/__main__.py
docker_ci_deploy-0.3.0.dist-info/top_level.txt
docker_ci_deploy-0.3.0.dist-info/entry_points.txt
docker_ci_deploy-0.3.0.dist-info/METADATA
docker_ci_deploy-0.3.0.dist-info/DESCRIPTION.rst
docker_ci_deploy-0.3.0.dist-info/LICENSE.txt
docker_ci_deploy-0.3.0.dist-info/metadata.json
docker_ci_deploy-0.3.0.dist-info/WHEEL
docker_ci_deploy-0.3.0.dist-info/RECORD
