Metadata-Version: 2.0
Name: docker-ci-deploy
Version: 0.3.0
Summary: Python script to help push Docker images to a registry using CI services
Home-page: https://github.com/praekeltfoundation/docker-ci-deploy
Author: Praekelt.org SRE team
Author-email: sre@praekelt.org
License: MIT
Platform: UNKNOWN
Classifier: Development Status :: 4 - Beta
Classifier: License :: OSI Approved :: MIT License
Classifier: Programming Language :: Python :: 2
Classifier: Programming Language :: Python :: 2.7
Classifier: Programming Language :: Python :: 3
Classifier: Programming Language :: Python :: 3.4
Classifier: Programming Language :: Python :: 3.5
Classifier: Programming Language :: Python :: 3.6
